johnsnowlabs/__init__.py
johnsnowlabs/finance.py
johnsnowlabs/lab.py
johnsnowlabs/legal.py
johnsnowlabs/llm.py
johnsnowlabs/medical.py
johnsnowlabs/nlp.py
johnsnowlabs/settings.py
johnsnowlabs/visual.py
johnsnowlabs/viz.py
johnsnowlabs/abstract_base/__init__.py
johnsnowlabs/abstract_base/base_enum.py
johnsnowlabs/abstract_base/lib_resolver.py
johnsnowlabs/abstract_base/pydantic_model.py
johnsnowlabs/abstract_base/software_product.py
johnsnowlabs/auto_install/__init__.py
johnsnowlabs/auto_install/install_flow.py
johnsnowlabs/auto_install/install_software.py
johnsnowlabs/auto_install/jsl_home.py
johnsnowlabs/auto_install/offline_install.py
johnsnowlabs/auto_install/softwares.py
johnsnowlabs/auto_install/databricks/__init__.py
johnsnowlabs/auto_install/databricks/dbfs.py
johnsnowlabs/auto_install/databricks/endpoints.py
johnsnowlabs/auto_install/databricks/install_utils.py
johnsnowlabs/auto_install/databricks/work_utils.py
johnsnowlabs/auto_install/emr/__init__.py
johnsnowlabs/auto_install/emr/enums.py
johnsnowlabs/auto_install/emr/install_utils.py
johnsnowlabs/auto_install/emr/utils.py
johnsnowlabs/auto_install/emr/work_utils.py
johnsnowlabs/auto_install/glue/__init__.py
johnsnowlabs/auto_install/glue/install_utils.py
johnsnowlabs/auto_install/glue/utils.py
johnsnowlabs/auto_install/health_checks/__init__.py
johnsnowlabs/auto_install/health_checks/benchmark_test.py
johnsnowlabs/auto_install/health_checks/endpoint_test.py
johnsnowlabs/auto_install/health_checks/generate_test.py
johnsnowlabs/auto_install/health_checks/hc_test.py
johnsnowlabs/auto_install/health_checks/load_predict_test.py
johnsnowlabs/auto_install/health_checks/nlp_test.py
johnsnowlabs/auto_install/health_checks/ocr_test.py
johnsnowlabs/auto_install/health_checks/report.py
johnsnowlabs/auto_install/lib_resolvers/__init__.py
johnsnowlabs/auto_install/lib_resolvers/hc_installer.py
johnsnowlabs/auto_install/lib_resolvers/nlp_installer.py
johnsnowlabs/auto_install/lib_resolvers/ocr_installer.py
johnsnowlabs_for_databricks_by_ckl-5.1.8rc16.dist-info/LICENSE
johnsnowlabs_for_databricks_by_ckl-5.1.8rc16.dist-info/METADATA
johnsnowlabs_for_databricks_by_ckl-5.1.8rc16.dist-info/WHEEL
johnsnowlabs_for_databricks_by_ckl-5.1.8rc16.dist-info/top_level.txt
johnsnowlabs_for_databricks_by_ckl-5.1.8rc16.dist-info/RECORD
